sbom4windows/__init__.py
sbom4windows/cli.py
sbom4windows/extract.py
sbom4windows/generate.py
sbom4windows/pecheck.py
sbom4windows/peutils.py
sbom4windows/scanner.py
sbom4windows/version.py
sbom4windows-0.1.1.dist-info/LICENSE
sbom4windows-0.1.1.dist-info/METADATA
sbom4windows-0.1.1.dist-info/WHEEL
sbom4windows-0.1.1.dist-info/entry_points.txt
sbom4windows-0.1.1.dist-info/top_level.txt
sbom4windows-0.1.1.dist-info/RECORD
